zerotk/__init__.py
zerotk/_tests/test_gitignored/test_00/.gitignore
zerotk/_tests/test_gitignored/test_00/git-root.txt
zerotk/_tests/test_gitignored/test_00/included/alpha.txt
zerotk/_tests/test_gitignored/test_00/placed-holder.txt
zerotk/_tests/test_gitignored.py
zerotk/_tests/test_text.py
zerotk/_tests/test_wiring.py
zerotk/_tests/test_yaml.py
zerotk/deps/__init__.py
zerotk/deps/_deps.py
zerotk/deps/_tests/test_deps.py
zerotk/gitignored.py
zerotk/path.py
zerotk/pushpop.py
zerotk/version.py
zerotk/yaml.py
zops/__init__.py
zops/__main__.py
zops/_tests/test_zops.py
zops/aws/__init__.py
zops/aws/__main__.py
zops/aws/autoscaling.py
zops/aws/cli.py
zops/aws/cli_config.py
zops/aws/cluster.py
zops/aws/config.yml
zops/aws/ecs.py
zops/aws/image.py
zops/aws/instance.py
zops/aws/utils.py
zops/aws/utils_click.py
zops/aws/utils_shell.py
zz/__init__.py
zz/__main__.py
zz/aag/__init__.py
zz/anatomy/__init__.py
zz/anatomy/assertions.py
zz/anatomy/layers/__init__.py
zz/anatomy/layers/feature.py
zz/anatomy/layers/playbook.py
zz/anatomy/layers/registry.py
zz/anatomy/layers/tree.py
zz/cli/aag.py
zz/cli/aws.py
zz/cli/codegen.py
zz/cli/git.py
zz/cli/test.py
zz/cli/tf.py
zz/codegen/__init__.py
zz/services/__init__.py
zz/services/aws.py
zz/services/aws_provider.py
zz/services/caches.py
zz/services/cmd_wrapper.py
zz/services/config.py
zz/services/console.py
zz/services/filesystem.py
zz/services/formatter.py
zz/services/git.py
zz/services/requests.py
zz/services/subprocess.py
zz/services/template_engine.py
zz/services/terraform.py
zz/services/text.py
zerotk_zops-2.0.0.dist-info/METADATA
zerotk_zops-2.0.0.dist-info/WHEEL
zerotk_zops-2.0.0.dist-info/entry_points.txt
zerotk_zops-2.0.0.dist-info/RECORD
